ascii_forge/__init__.py
ascii_forge/__main__.py
ascii_forge/config.py
ascii_forge/converter.py
ascii_forge/utils.py
ascii_forge-1.0.0.dist-info/LICENSE
ascii_forge-1.0.0.dist-info/METADATA
ascii_forge-1.0.0.dist-info/WHEEL
ascii_forge-1.0.0.dist-info/entry_points.txt
ascii_forge-1.0.0.dist-info/top_level.txt
ascii_forge-1.0.0.dist-info/RECORD
