Metadata-Version: 2.1
Name: ascii-forge
Version: 1.0.0
Summary: Turn your images into ASCII art from your terminal
Home-page: https://github.com/kanakOS01/ascii-forge
Author: Kanak Tanwar
Author-email: kanaktanwarpro@gmail.com
Project-URL: GitHub Repository, https://github.com/kanakOS01/ascii-forge
Project-URL: PyPI Project Page, https://pypi.org/project/ascii-forge/
Keywords: ascii-forge ascii forge ascii-art art
Classifier: Programming Language :: Python :: 3
Classifier: License :: OSI Approved :: MIT License
Requires-Python: >=3.6
License-File: LICENSE
Requires-Dist: Click
Requires-Dist: Pillow
Requires-Dist: Colorama
